{
  "services": [
    {
      "city": "Архангельск",
      "clubs": [
        {
          "id": 1,
          "name": "Архангельск на Московском",
          "address": "пр. Московский, д. 33",
          "isPool": true,
          "category": "STD",
          "products": [
            {
              "product_id": "425262",
              "product_price": "1900",
              "product_name": "1 месяц Утро Архангельск Подписка",
              "product_type": "morning"
            },
            {
              "product_id": "425417",
              "product_price": "2900",
              "product_name": "1 месяц Архангельск Подписка",
              "product_type": "full"
            },
            {
              "product_id": "428704",
              "product_price": "3500",
              "product_name": "Мультикарта 1 месяц Архангельск Подписка",
              "product_type": "mc_full"
            },
            {
              "product_id": "425209",
              "product_price": "1990",
              "product_name": "Первоначальный платеж",
              "product_type": "first_pay"
            }
          ]
        },
        {
          "id": 2,
          "name": "Архангельск на Никольском",
          "address": "пр-т Никольский, 110",
          "isPool": true,
          "category": "STD",
          "products": [
            {
              "product_id": "428705",
              "product_price": "1900",
              "product_name": "1 месяц Утро Архангельск Подписка",
              "product_type": "morning"
            },
            {
              "product_id": "428706",
              "product_price": "2900",
              "product_name": "1 месяц Архангельск Подписка",
              "product_type": "full"
            },
            {
              "product_id": "428703",
              "product_price": "3500",
              "product_name": "Мультикарта 1 месяц Архангельск Подписка",
              "product_type": "mc_full"
            },
            {
              "product_id": "428707",
              "product_price": "1990",
              "product_name": "Первоначальный платеж",
              "product_type": "first_pay"
            }
          ]
        }
      ]
    },
    {
      "city": "Нижний Новгород",
      "clubs": [
        {
          "id": 1,
          "name": "FH Н.Новгород Московский",
          "address": "Московское шоссе, д.12",
          "isPool": true,
          "category": "STD",
          "products": [
            {
              "product_id": "425264",
              "product_price": "1900",
              "product_name": "1 месяц Утро Нижний Новгород Подписка",
              "product_type": "morning"
            },
            {
              "product_id": "425253",
              "product_price": "2900",
              "product_name": "1 месяц Подписка Нижний Новгород",
              "product_type": "full"
            },
            {
              "product_id": "425277",
              "product_price": "3500",
              "product_name": "Мультикарта 1 месяц Нижний Новгород Подписка",
              "product_type": "mc_full"
            },
            {
              "product_id": "425217",
              "product_price": "1990",
              "product_name": "Первоначальный платеж",
              "product_type": "first_pay"
            }
          ]
        },
        {
          "id": 2,
          "name": "FH Н.Новгород Цветы",
          "address": "ул. Цветочная, 12",
          "isPool": true,
          "category": "STD",
          "products": [
            {
              "product_id": "425265",
              "product_price": "1900",
              "product_name": "1 месяц Утро Нижний Новгород Подписка",
              "product_type": "morning"
            },
            {
              "product_id": "425278",
              "product_price": "2900",
              "product_name": "1 месяц Подписка Нижний Новгород",
              "product_type": "full"
            },
            {
              "product_id": "428703",
              "product_price": "3500",
              "product_name": "Мультикарта 1 месяц Нижний Новгород Подписка",
              "product_type": "mc_full"
            },
            {
              "product_id": "425212",
              "product_price": "1990",
              "product_name": "Первоначальный платеж",
              "product_type": "first_pay"
            }
          ]
        }
      ]
    },
    {
      "city": "Ижевск",
      "clubs": [
        {
          "id": 1,
          "name": "Матрица Молл",
          "address": "ул. Баранова д. 87",
          "isPool": true,
          "category": "STD",
          "products": [
            {
              "product_id": "425146",
              "product_price": "1900",
              "product_name": "1 месяц Утро Ижевск Подписка",
              "product_type": "morning"
            },
            {
              "product_id": "425184",
              "product_price": "2900",
              "product_name": "1 месяц Ижевск Подписка",
              "product_type": "full"
            },
            {
              "product_id": "425140",
              "product_price": "3500",
              "product_name": "Мультикарта 1 месяц Ижевск Подписка",
              "product_type": "mc_full"
            },
            {
              "product_id": "425206",
              "product_price": "1990",
              "product_name": "Первоначальный платеж",
              "product_type": "first_pay"
            }
          ]
        },
        {
          "id": 2,
          "name": "10 лет Октября",
          "address": "ул. 10 лет Октября, 17А",
          "isPool": true,
          "category": "STD",
          "products": [
            {
              "product_id": "425147",
              "product_price": "1900",
              "product_name": "1 месяц Утро Ижевск Подписка",
              "product_type": "morning"
            },
            {
              "product_id": "425185",
              "product_price": "2900",
              "product_name": "1 месяц Подписка Ижевск",
              "product_type": "full"
            },
            {
              "product_id": "425141",
              "product_price": "3500",
              "product_name": "Мультикарта 1 месяц Ижевск Подписка",
              "product_type": "mc_full"
            },
            {
              "product_id": "425207",
              "product_price": "1990",
              "product_name": "Первоначальный платеж",
              "product_type": "first_pay"
            }
          ]
        },
        {
          "id": 3,
          "name": "Молодежная",
          "address": "ул. Молодежная, 107 Б",
          "isPool": true,
          "category": "STD",
          "products": [
            {
              "product_id": "425145",
              "product_price": "1900",
              "product_name": "1 месяц Утро Ижевск Подписка",
              "product_type": "morning"
            },
            {
              "product_id": "425183",
              "product_price": "2900",
              "product_name": "1 месяц Подписка Ижевск",
              "product_type": "full"
            },
            {
              "product_id": "425139",
              "product_price": "3500",
              "product_name": "Мультикарта 1 месяц Ижевск Подписка",
              "product_type": "mc_full"
            },
            {
              "product_id": "425205",
              "product_price": "1990",
              "product_name": "Первоначальный платеж",
              "product_type": "first_pay"
            }
          ]
        }
      ]
    },
    {
      "city": "Ярославль",
      "clubs": [
        {
          "id": 1,
          "name": "Ярославль Нагорный",
          "address": "ул. Дорожная, д. 6б",
          "isPool": true,
          "category": "STD",
          "products": [
            {
              "product_id": "425271",
              "product_price": "1900",
              "product_name": "1 месяц Утро Ярославль Подписка",
              "product_type": "morning"
            },
            {
              "product_id": "425273",
              "product_price": "2900",
              "product_name": "1 месяц Подписка Ярославль",
              "product_type": "full"
            },
            {
              "product_id": "425281",
              "product_price": "3500",
              "product_name": "Мультикарта 1 месяц Ярославль Подписка",
              "product_type": "mc_full"
            },
            {
              "product_id": "425204",
              "product_price": "1990",
              "product_name": "Первоначальный платеж",
              "product_type": "first_pay"
            }
          ]
        },
        {
          "id": 2,
          "name": "Ярославль Республиканская",
          "address": "ул. Республиканская, д.61",
          "isPool": true,
          "category": "STD",
          "products": [
            {
              "product_id": "425272",
              "product_price": "1900",
              "product_name": "1 месяц Утро Ярославль Подписка",
              "product_type": "morning"
            },
            {
              "product_id": "425274",
              "product_price": "2900",
              "product_name": "1 месяц Подписка Ярославль",
              "product_type": "full"
            },
            {
              "product_id": "425282",
              "product_price": "3500",
              "product_name": "Мультикарта 1 Ярославль месяц Подписка",
              "product_type": "mc_full"
            },
            {
              "product_id": "425187",
              "product_price": "1990",
              "product_name": "Первоначальный платеж",
              "product_type": "first_pay"
            }
          ]
        }
      ]
    },
    {
      "city": "Казань",
      "clubs": [
        {
          "id": 1,
          "name": "Казань Победы",
          "address": "пр. Победы, д. 173",
          "isPool": true,
          "category": "STD",
          "products": [
            {
              "product_id": "425255",
              "product_price": "1900",
              "product_name": "1 месяц Утро Казань Подписка",
              "product_type": "morning"
            },
            {
              "product_id": "425254",
              "product_price": "2900",
              "product_name": "1 месяц Казань Подписка",
              "product_type": "full"
            },
            {
              "product_id": "425276",
              "product_price": "3500",
              "product_name": "Мультикарта 1 месяц Казань Подписка",
              "product_type": "mc_full"
            },
            {
              "product_id": "425201",
              "product_price": "1990",
              "product_name": "Первоначальный платеж",
              "product_type": "first_pay"
            }
          ]
        },
        {
          "id": 2,
          "name": "Казань Спартаковский",
          "address": "ул. Спартаковская, д. 88 стр.А",
          "isPool": true,
          "category": "STD",
          "products": [
            {
              "product_id": "425251",
              "product_price": "1900",
              "product_name": "1 месяц Утро Казань Подписка",
              "product_type": "morning"
            },
            {
              "product_id": "425250",
              "product_price": "2900",
              "product_name": "1 месяц Казань Подписка",
              "product_type": "full"
            },
            {
              "product_id": "425275",
              "product_price": "3500",
              "product_name": "Мультикарта 1 месяц Казань Подписка",
              "product_type": "mc_full"
            },
            {
              "product_id": "425213",
              "product_price": "1990",
              "product_name": "Первоначальный платеж",
              "product_type": "first_pay"
            }
          ]
        }
      ]
    },
    {
      "city": "Набережные Челны",
      "clubs": [
        {
          "id": 1,
          "name": "Набережные Челны Санрайз Сити",
          "address": "пр-т Сююмбике 40А, ТЦ Sunrise",
          "isPool": true,
          "category": "STD",
          "products": [
            {
              "product_id": "425263",
              "product_price": "1900",
              "product_name": "1 месяц Утро Набережные Челны Подписка",
              "product_type": "morning"
            },
            {
              "product_id": "425256",
              "product_price": "2900",
              "product_name": "1 месяц Набережные Челны Подписка",
              "product_type": "full"
            },
            {
              "product_id": "425192",
              "product_price": "1990",
              "product_name": "Первоначальный платеж",
              "product_type": "first_pay"
            }
          ]
        }
      ]
    },
    {
      "city": "Петрозаводск",
      "clubs": [
        {
          "id": 1,
          "name": "Петрозаводск Лесной",
          "address": "пр. Лесной д. 47а ТРК «ЛОТОС PLAZA»",
          "isPool": true,
          "category": "STD",
          "products": [
            {
              "product_id": "425266",
              "product_price": "1900",
              "product_name": "1 месяц Утро Петрозаводск Подписка",
              "product_type": "morning"
            },
            {
              "product_id": "425257",
              "product_price": "2900",
              "product_name": "1 месяц Петрозаводск Подписка",
              "product_type": "full"
            },
            {
              "product_id": "425203",
              "product_price": "1990",
              "product_name": "Первоначальный платеж",
              "product_type": "first_pay"
            }
          ]
        }
      ]
    },
    {
      "city": "Рязань",
      "clubs": [
        {
          "id": 1,
          "name": "Рязань Чкалова",
          "address": "ул.Чкалова, 18",
          "isPool": true,
          "category": "STD",
          "products": [
            {
              "product_id": "425267",
              "product_price": "1900",
              "product_name": "1 месяц Утро Рязань Подписка",
              "product_type": "morning"
            },
            {
              "product_id": "425258",
              "product_price": "2900",
              "product_name": "1 месяц Рязань Подписка",
              "product_type": "full"
            },
            {
              "product_id": "425202",
              "product_price": "1990",
              "product_name": "Первоначальный платеж",
              "product_type": "first_pay"
            }
          ]
        }
      ]
    },
    {
      "city": "Тольятти",
      "clubs": [
        {
          "id": 1,
          "name": "Тольятти Революционная",
          "address": "ул.Революционная, 52а",
          "isPool": true,
          "category": "STD",
          "products": [
            {
              "product_id": "425134",
              "product_price": "1900",
              "product_name": "1 месяц Утро Тольятти Подписка",
              "product_type": "morning"
            },
            {
              "product_id": "425135",
              "product_price": "2900",
              "product_name": "1 месяц Тольятти Подписка",
              "product_type": "full"
            },
            {
              "product_id": "425211",
              "product_price": "1990",
              "product_name": "Первоначальный платеж",
              "product_type": "first_pay"
            }
          ]
        }
      ]
    },
    {
      "city": "Тула",
      "clubs": [
        {
          "id": 1,
          "name": "Тула Оборонная",
          "address": "ул. Оборонная 102 б",
          "isPool": true,
          "category": "STD",
          "products": [
            {
              "product_id": "425268",
              "product_price": "1900",
              "product_name": "1 месяц Утро Тула Подписка",
              "product_type": "morning"
            },
            {
              "product_id": "425259",
              "product_price": "2900",
              "product_name": "1 месяц Тула Подписка",
              "product_type": "full"
            },
            {
              "product_id": "425189",
              "product_price": "1990",
              "product_name": "Первоначальный платеж",
              "product_type": "first_pay"
            }
          ]
        }
      ]
    },
    {
      "city": "Ульяновск",
      "clubs": [
        {
          "id": 1,
          "name": "Ульяновск Октябрьская",
          "address": "ул. Октябрьская, 22",
          "isPool": true,
          "category": "STD",
          "products": [
            {
              "product_id": "425270",
              "product_price": "1900",
              "product_name": "1 месяц Утро Ульяновск Подписка",
              "product_type": "morning"
            },
            {
              "product_id": "425261",
              "product_price": "2900",
              "product_name": "1 месяц Ульяновск Подписка",
              "product_type": "full"
            },
            {
              "product_id": "425280",
              "product_price": "3500",
              "product_name": "Мультикарта 1 месяц Ульяновск Подписка",
              "product_type": "mc_full"
            },
            {
              "product_id": "425200",
              "product_price": "1990",
              "product_name": "Первоначальный платеж",
              "product_type": "first_pay"
            }
          ]
        },
        {
          "id": 2,
          "name": "Ульяновск Созидателей",
          "address": "пр. Созидателей, №116",
          "isPool": true,
          "category": "STD",
          "products": [
            {
              "product_id": "425269",
              "product_price": "1900",
              "product_name": "1 месяц Утро Ульяновск Подписка",
              "product_type": "morning"
            },
            {
              "product_id": "425260",
              "product_price": "2900",
              "product_name": "1 месяц Ульяновск Подписка",
              "product_type": "full"
            },
            {
              "product_id": "425279",
              "product_price": "3500",
              "product_name": "Мультикарта 1 месяц Ульяновск Подписка",
              "product_type": "mc_full"
            },
            {
              "product_id": "425208",
              "product_price": "1990",
              "product_name": "Первоначальный платеж",
              "product_type": "first_pay"
            }
          ]
        }
      ]
    },
    {
      "city": "Самара",
      "clubs": [
        {
          "id": 1,
          "name": "Монте Роза",
          "address": "Московское ш., 4, корп. 4",
          "isPool": true,
          "category": "STD",
          "products": [
            {
              "product_id": "425416",
              "product_price": "1900",
              "product_name": "1 месяц Утро Самара Подписка",
              "product_type": "morning"
            },
            {
              "product_id": "425150",
              "product_price": "2900",
              "product_name": "1 месяц Самара Подписка",
              "product_type": "full"
            },
            {
              "product_id": "425137",
              "product_price": "3500",
              "product_name": "Мультикарта 1 месяц Самара Подписка",
              "product_type": "mc_full"
            },
            {
              "product_id": "425193",
              "product_price": "1990",
              "product_name": "Первоначальный платеж",
              "product_type": "first_pay"
            }
          ]
        },
        {
          "id": 2,
          "name": "Гудок",
          "address": "Красноармейская ул., 131",
          "isPool": true,
          "category": "STD",
          "products": [
            {
              "product_id": "425142",
              "product_price": "1900",
              "product_name": "1 месяц Утро Самара Подписка",
              "product_type": "morning"
            },
            {
              "product_id": "425149",
              "product_price": "2900",
              "product_name": "1 месяц Самара Подписка",
              "product_type": "full"
            },
            {
              "product_id": "425136",
              "product_price": "3500",
              "product_name": "Мультикарта 1 месяц Самара Подписка",
              "product_type": "mc_full"
            },
            {
              "product_id": "425191",
              "product_price": "1990",
              "product_name": "Первоначальный платеж",
              "product_type": "first_pay"
            }
          ]
        },
        {
          "id": 3,
          "name": "Амбар",
          "address": "Южное шоссе д. 5",
          "isPool": true,
          "category": "STD",
          "products": [
            {
              "product_id": "425144",
              "product_price": "1900",
              "product_name": "1 месяц Утро Самара Подписка",
              "product_type": "morning"
            },
            {
              "product_id": "425152",
              "product_price": "2900",
              "product_name": "1 месяц Самара Подписка",
              "product_type": "full"
            },
            {
              "product_id": "425148",
              "product_price": "3500",
              "product_name": "Мультикарта 1 месяц Самара Подписка",
              "product_type": "mc_full"
            },
            {
              "product_id": "425210",
              "product_price": "1990",
              "product_name": "Первоначальный платеж",
              "product_type": "first_pay"
            }
          ]
        },
        {
          "id": 4,
          "name": "Шипка",
          "address": "Ул. Стара Загора, 58",
          "isPool": true,
          "category": "STD",
          "products": [
            {
              "product_id": "425151",
              "product_price": "2900",
              "product_name": "1 месяц Самара Подписка",
              "product_type": "full"
            },
            {
              "product_id": "425138",
              "product_price": "3500",
              "product_name": "Мультикарта 1 месяц Самара Подписка",
              "product_type": "mc_full"
            },
            {
              "product_id": "425199",
              "product_price": "1990",
              "product_name": "Первоначальный платеж",
              "product_type": "first_pay"
            }
          ]
        }
      ]
    },
    {
      "city": "Санкт-Петербург",
      "clubs": [
        {
          "id": 1,
          "name": "Васильевский",
          "address": "пр. Большой В.О., д. 68А",
          "isPool": false,
          "category": "STD",
          "products": [
            {
              "product_id": "425155",
              "product_price": "1500",
              "product_name": "1 месяц Утро СПБ Подписка",
              "product_type": "morning"
            },
            {
              "product_id": "425159",
              "product_price": "1900",
              "product_name": "1 месяц СПБ Подписка",
              "product_type": "full"
            },
            {
              "product_id": "425163",
              "product_price": "3500",
              "product_name": "Мультикарта 1 месяц СПБ Подписка",
              "product_type": "mc_full"
            },
            {
              "product_id": "425240",
              "product_price": "1990",
              "product_name": "Первоначальный платеж",
              "product_type": "first_pay"
            }
          ]
        },
        {
          "id": 2,
          "name": "Наставников",
          "address": "пр. Наставников, д.24 к.1",
          "isPool": false,
          "category": "STD",
          "products": [
            {
              "product_id": "425156",
              "product_price": "1500",
              "product_name": "1 месяц Утро СПБ Подписка",
              "product_type": "morning"
            },
            {
              "product_id": "425160",
              "product_price": "1900",
              "product_name": "1 месяц СПБ Подписка",
              "product_type": "full"
            },
            {
              "product_id": "425447",
              "product_price": "3500",
              "product_name": "Мультикарта 1 месяц СПБ Подписка",
              "product_type": "mc_full"
            },
            {
              "product_id": "425243",
              "product_price": "1990",
              "product_name": "Первоначальный платеж",
              "product_type": "first_pay"
            }
          ]
        },
        {
          "id": 3,
          "name": "Светлановский",
          "address": "пр. Энгельса, д.33, корп. 1",
          "isPool": false,
          "category": "STD",
          "products": [
            {
              "product_id": "425154",
              "product_price": "1500",
              "product_name": "1 месяц Утро СПБ Подписка",
              "product_type": "morning"
            },
            {
              "product_id": "425158",
              "product_price": "1900",
              "product_name": "1 месяц СПБ Подписка",
              "product_type": "full"
            },
            {
              "product_id": "425162",
              "product_price": "3500",
              "product_name": "Мультикарта 1 месяц СПБ Подписка",
              "product_type": "mc_full"
            },
            {
              "product_id": "425238",
              "product_price": "1990",
              "product_name": "Первоначальный платеж",
              "product_type": "first_pay"
            }
          ]
        },
        {
          "id": 4,
          "name": "Петергоф",
          "address": "Петергоф, Санкт-Петербургский пр., д.60",
          "isPool": false,
          "category": "STD",
          "products": [
            {
              "product_id": "425153",
              "product_price": "1500",
              "product_name": "1 месяц Утро СПБ Подписка",
              "product_type": "morning"
            },
            {
              "product_id": "425157",
              "product_price": "1900",
              "product_name": "1 месяц СПБ Подписка",
              "product_type": "full"
            },
            {
              "product_id": "425459",
              "product_price": "3500",
              "product_name": "Мультикарта 1 месяц СПБ Подписка",
              "product_type": "mc_full"
            },
            {
              "product_id": "425228",
              "product_price": "1990",
              "product_name": "Первоначальный платеж",
              "product_type": "first_pay"
            }
          ]
        },
        {
          "id": 5,
          "name": "FH на Салова",
          "address": "ул. Салова, 61, строение 1",
          "isPool": true,
          "category": "PRM",
          "products": [
            {
              "product_id": "425436",
              "product_price": "1900",
              "product_name": "1 месяц Утро СПБ Подписка",
              "product_type": "morning"
            },
            {
              "product_id": "425428",
              "product_price": "2900",
              "product_name": "1 месяц СПБ Подписка",
              "product_type": "full"
            },
            {
              "product_id": "425471",
              "product_price": "3500",
              "product_name": "Мультикарта 1 месяц СПБ Подписка",
              "product_type": "mc_full"
            },
            {
              "product_id": "425424",
              "product_price": "1990",
              "product_name": "Первоначальный платеж",
              "product_type": "first_pay"
            }
          ]
        },
        {
          "id": 6,
          "name": "FH в Охта Молле",
          "address": "ТРЦ \"Охта Молл\", Брантовская дор., 3",
          "isPool": false,
          "category": "PRM",
          "products": [
            {
              "product_id": "425437",
              "product_price": "1900",
              "product_name": "1 месяц Утро СПБ Подписка",
              "product_type": "morning"
            },
            {
              "product_id": "425429",
              "product_price": "2900",
              "product_name": "1 месяц СПБ Подписка",
              "product_type": "full"
            },
            {
              "product_id": "425470",
              "product_price": "3500",
              "product_name": "Мультикарта 1 месяц СПБ Подписка",
              "product_type": "mc_full"
            },
            {
              "product_id": "425425",
              "product_price": "1990",
              "product_name": "Первоначальный платеж",
              "product_type": "first_pay"
            }
          ]
        },
        {
          "id": 7,
          "name": "FH Prestige на Хошимина",
          "address": "Выборгское шоссе, д. 15А",
          "isPool": true,
          "category": "PRG",
          "products": [
            {
              "product_id": "425439",
              "product_price": "1900",
              "product_name": "1 месяц Утро СПБ Подписка",
              "product_type": "morning"
            },
            {
              "product_id": "425431",
              "product_price": "2900",
              "product_name": "1 месяц СПБ Подписка",
              "product_type": "full"
            },
            {
              "product_id": "425440",
              "product_price": "3500",
              "product_name": "Мультикарта 1 месяц СПБ Подписка",
              "product_type": "mc_full"
            },
            {
              "product_id": "425427",
              "product_price": "1990",
              "product_name": "Первоначальный платеж",
              "product_type": "first_pay"
            }
          ]
        },
        {
          "id": 8,
          "name": "FH в Гатчине",
          "address": "Гатчина, ул. Генерала Кныша, д.2А",
          "isPool": true,
          "category": "STD",
          "products": [
            {
              "product_id": "425337",
              "product_price": "1900",
              "product_name": "1 месяц Утро СПБ Подписка",
              "product_type": "morning"
            },
            {
              "product_id": "425295",
              "product_price": "2900",
              "product_name": "1 месяц СПБ Подписка",
              "product_type": "full"
            },
            {
              "product_id": "425453",
              "product_price": "3500",
              "product_name": "Мультикарта 1 месяц СПБ Подписка",
              "product_type": "mc_full"
            },
            {
              "product_id": "425235",
              "product_price": "1990",
              "product_name": "Первоначальный платеж",
              "product_type": "first_pay"
            }
          ]
        },
        {
          "id": 9,
          "name": "FH в Девяткино",
          "address": "Новое Девяткино, Главная д.60",
          "isPool": true,
          "category": "STD",
          "products": [
            {
              "product_id": "425330",
              "product_price": "1900",
              "product_name": "1 месяц Утро СПБ Подписка",
              "product_type": "morning"
            },
            {
              "product_id": "425288",
              "product_price": "2900",
              "product_name": "1 месяц СПБ Подписка",
              "product_type": "full"
            },
            {
              "product_id": "425446",
              "product_price": "3500",
              "product_name": "Мультикарта 1 месяц СПБ Подписка",
              "product_type": "mc_full"
            },
            {
              "product_id": "425244",
              "product_price": "1990",
              "product_name": "Первоначальный платеж",
              "product_type": "first_pay"
            }
          ]
        },
        {
          "id": 10,
          "name": "FH в Кудрово",
          "address": "дер. Кудрово, Европейский пр. 21, стр.1, лит.В",
          "isPool": true,
          "category": "STD",
          "products": [
            {
              "product_id": "425399",
              "product_price": "1900",
              "product_name": "1 месяц Утро СПБ Подписка",
              "product_type": "morning"
            },
            {
              "product_id": "425307",
              "product_price": "2900",
              "product_name": "1 месяц СПБ Подписка",
              "product_type": "full"
            },
            {
              "product_id": "425463",
              "product_price": "3500",
              "product_name": "Мультикарта 1 месяц СПБ Подписка",
              "product_type": "mc_full"
            },
            {
              "product_id": "425223",
              "product_price": "1990",
              "product_name": "Первоначальный платеж",
              "product_type": "first_pay"
            }
          ]
        },
        {
          "id": 11,
          "name": "FH в Лахте",
          "address": "Лахтинский пр., д.85",
          "isPool": true,
          "category": "STD",
          "products": [
            {
              "product_id": "425328",
              "product_price": "1900",
              "product_name": "1 месяц Утро СПБ Подписка",
              "product_type": "morning"
            },
            {
              "product_id": "425286",
              "product_price": "2900",
              "product_name": "1 месяц СПБ Подписка",
              "product_type": "full"
            },
            {
              "product_id": "425444",
              "product_price": "3500",
              "product_name": "Мультикарта 1 месяц СПБ Подписка",
              "product_type": "mc_full"
            },
            {
              "product_id": "425246",
              "product_price": "1990",
              "product_name": "Первоначальный платеж",
              "product_type": "first_pay"
            }
          ]
        },
        {
          "id": 12,
          "name": "FH в Мурино",
          "address": "г. Мурино, ул.Шувалова д.11",
          "isPool": true,
          "category": "STD",
          "products": [
            {
              "product_id": "425405",
              "product_price": "1900",
              "product_name": "1 месяц Утро СПБ Подписка",
              "product_type": "morning"
            },
            {
              "product_id": "425313",
              "product_price": "2900",
              "product_name": "1 месяц СПБ Подписка",
              "product_type": "full"
            },
            {
              "product_id": "425468",
              "product_price": "3500",
              "product_name": "Мультикарта 1 месяц СПБ Подписка",
              "product_type": "mc_full"
            },
            {
              "product_id": "425216",
              "product_price": "1990",
              "product_name": "Первоначальный платеж",
              "product_type": "first_pay"
            }
          ]
        },
        {
          "id": 13,
          "name": "FH в Рыбацком",
          "address": "пер. Скачков, д. 5",
          "isPool": true,
          "category": "STD",
          "products": [
            {
              "product_id": "425341",
              "product_price": "1900",
              "product_name": "1 месяц Утро СПБ Подписка",
              "product_type": "morning"
            },
            {
              "product_id": "425299",
              "product_price": "2900",
              "product_name": "1 месяц СПБ Подписка",
              "product_type": "full"
            },
            {
              "product_id": "425355",
              "product_price": "3500",
              "product_name": "Мультикарта 1 месяц СПБ Подписка",
              "product_type": "mc_full"
            },
            {
              "product_id": "425231",
              "product_price": "1990",
              "product_name": "Первоначальный платеж",
              "product_type": "first_pay"
            }
          ]
        },
        {
          "id": 14,
          "name": "FH в Славянке",
          "address": "п. Шушары, ул. Ростовская, д. 20",
          "isPool": true,
          "category": "STD",
          "products": [
            {
              "product_id": "425409",
              "product_price": "1900",
              "product_name": "1 месяц Утро СПБ Подписка",
              "product_type": "morning"
            },
            {
              "product_id": "425317",
              "product_price": "2900",
              "product_name": "1 месяц СПБ Подписка",
              "product_type": "full"
            },
            {
              "product_id": "425473",
              "product_price": "3500",
              "product_name": "Мультикарта 1 месяц СПБ Подписка",
              "product_type": "mc_full"
            },
            {
              "product_id": "425197",
              "product_price": "1990",
              "product_name": "Первоначальный платеж",
              "product_type": "first_pay"
            }
          ]
        },
        {
          "id": 15,
          "name": "FH в Шушарах",
          "address": "п.Шушары, Новгородский пр-т, д.6, к.2, строение 1",
          "isPool": true,
          "category": "STD",
          "products": [
            {
              "product_id": "425411",
              "product_price": "1900",
              "product_name": "1 месяц Утро СПБ Подписка",
              "product_type": "morning"
            },
            {
              "product_id": "425319",
              "product_price": "2900",
              "product_name": "1 месяц СПБ Подписка",
              "product_type": "full"
            },
            {
              "product_id": "425475",
              "product_price": "3500",
              "product_name": "Мультикарта 1 месяц СПБ Подписка",
              "product_type": "mc_full"
            },
            {
              "product_id": "425195",
              "product_price": "1990",
              "product_name": "Первоначальный платеж",
              "product_type": "first_pay"
            }
          ]
        },
        {
          "id": 16,
          "name": "FH в Янино",
          "address": "Янино, ул. Ветрянных мельниц, з/у № 3",
          "isPool": true,
          "category": "STD",
          "products": [
            {
              "product_id": "425413",
              "product_price": "1900",
              "product_name": "1 месяц Утро СПБ Подписка",
              "product_type": "morning"
            },
            {
              "product_id": "425322",
              "product_price": "2900",
              "product_name": "1 месяц СПБ Подписка",
              "product_type": "full"
            },
            {
              "product_id": "425477",
              "product_price": "3500",
              "product_name": "Мультикарта 1 месяц СПБ Подписка",
              "product_type": "mc_full"
            },
            {
              "product_id": "425190",
              "product_price": "1990",
              "product_name": "Первоначальный платеж",
              "product_type": "first_pay"
            }
          ]
        },
        {
          "id": 17,
          "name": "FH на Большевиков",
          "address": "пр. Большевиков, д.7 к1",
          "isPool": true,
          "category": "STD",
          "products": [
            {
              "product_id": "425400",
              "product_price": "1900",
              "product_name": "1 месяц Утро СПБ Подписка",
              "product_type": "morning"
            },
            {
              "product_id": "425308",
              "product_price": "2900",
              "product_name": "1 месяц СПБ Подписка",
              "product_type": "full"
            },
            {
              "product_id": "425363",
              "product_price": "3500",
              "product_name": "Мультикарта 1 месяц СПБ Подписка",
              "product_type": "mc_full"
            },
            {
              "product_id": "425222",
              "product_price": "1990",
              "product_name": "Первоначальный платеж",
              "product_type": "first_pay"
            }
          ]
        },
        {
          "id": 18,
          "name": "FH на Бульваре Новаторов",
          "address": "Бульвар Новаторов, д. 32",
          "isPool": true,
          "category": "STD",
          "products": [
            {
              "product_id": "425338",
              "product_price": "1900",
              "product_name": "1 месяц Утро СПБ Подписка",
              "product_type": "morning"
            },
            {
              "product_id": "425296",
              "product_price": "2900",
              "product_name": "1 месяц СПБ Подписка",
              "product_type": "full"
            },
            {
              "product_id": "425454",
              "product_price": "3500",
              "product_name": "Мультикарта 1 месяц СПБ Подписка",
              "product_type": "mc_full"
            },
            {
              "product_id": "425234",
              "product_price": "1990",
              "product_name": "Первоначальный платеж",
              "product_type": "first_pay"
            }
          ]
        },
        {
          "id": 19,
          "name": "FH на Ветеранов",
          "address": "пр. Ветеранов, 121",
          "isPool": true,
          "category": "STD",
          "products": [
            {
              "product_id": "425398",
              "product_price": "1900",
              "product_name": "1 месяц Утро СПБ Подписка",
              "product_type": "morning"
            },
            {
              "product_id": "425306",
              "product_price": "2900",
              "product_name": "1 месяц СПБ Подписка",
              "product_type": "full"
            },
            {
              "product_id": "425462",
              "product_price": "3500",
              "product_name": "Мультикарта 1 месяц СПБ Подписка",
              "product_type": "mc_full"
            },
            {
              "product_id": "425224",
              "product_price": "1990",
              "product_name": "Первоначальный платеж",
              "product_type": "first_pay"
            }
          ]
        },
        {
          "id": 20,
          "name": "FH на Выборгской наб.",
          "address": "Выборгская наб., д. 61",
          "isPool": true,
          "category": "STD",
          "products": [
            {
              "product_id": "425340",
              "product_price": "1900",
              "product_name": "1 месяц Утро СПБ Подписка",
              "product_type": "morning"
            },
            {
              "product_id": "425298",
              "product_price": "2900",
              "product_name": "1 месяц СПБ Подписка",
              "product_type": "full"
            },
            {
              "product_id": "425456",
              "product_price": "3500",
              "product_name": "Мультикарта 1 месяц СПБ Подписка",
              "product_type": "mc_full"
            },
            {
              "product_id": "425232",
              "product_price": "1990",
              "product_name": "Первоначальный платеж",
              "product_type": "first_pay"
            }
          ]
        },
        {
          "id": 21,
          "name": "FH на Гашека",
          "address": "ул. Я. Гашека, д. 17А",
          "isPool": true,
          "category": "STD",
          "products": [
            {
              "product_id": "425393",
              "product_price": "1900",
              "product_name": "1 месяц Утро СПБ Подписка",
              "product_type": "morning"
            },
            {
              "product_id": "425300",
              "product_price": "2900",
              "product_name": "1 месяц СПБ Подписка",
              "product_type": "full"
            },
            {
              "product_id": "425457",
              "product_price": "3500",
              "product_name": "Мультикарта 1 месяц СПБ Подписка",
              "product_type": "mc_full"
            },
            {
              "product_id": "425230",
              "product_price": "1990",
              "product_name": "Первоначальный платеж",
              "product_type": "first_pay"
            }
          ]
        },
        {
          "id": 22,
          "name": "FH на Дальневосточном",
          "address": "ул. Крыленко, д.14",
          "isPool": true,
          "category": "STD",
          "products": [
            {
              "product_id": "425401",
              "product_price": "1900",
              "product_name": "1 месяц Утро СПБ Подписка",
              "product_type": "morning"
            },
            {
              "product_id": "425309",
              "product_price": "2900",
              "product_name": "1 месяц СПБ Подписка",
              "product_type": "full"
            },
            {
              "product_id": "425464",
              "product_price": "3500",
              "product_name": "Мультикарта 1 месяц СПБ Подписка",
              "product_type": "mc_full"
            },
            {
              "product_id": "425221",
              "product_price": "1990",
              "product_name": "Первоначальный платеж",
              "product_type": "first_pay"
            }
          ]
        },
        {
          "id": 23,
          "name": "FH на Заречной",
          "address": "п. Парголово, Заречная улица, дом 15, к 1, стр 1",
          "isPool": true,
          "category": "STD",
          "products": [
            {
              "product_id": "425414",
              "product_price": "1900",
              "product_name": "1 месяц Утро СПБ Подписка",
              "product_type": "morning"
            },
            {
              "product_id": "425323",
              "product_price": "2900",
              "product_name": "1 месяц СПБ Подписка",
              "product_type": "full"
            },
            {
              "product_id": "425478",
              "product_price": "3500",
              "product_name": "Мультикарта 1 месяц СПБ Подписка",
              "product_type": "mc_full"
            },
            {
              "product_id": "425188",
              "product_price": "1990",
              "product_name": "Первоначальный платеж",
              "product_type": "first_pay"
            }
          ]
        },
        {
          "id": 24,
          "name": "FH на Камышовой",
          "address": "ул. Камышовая, д. 36, строение 1",
          "isPool": true,
          "category": "STD",
          "products": [
            {
              "product_id": "425412",
              "product_price": "1900",
              "product_name": "1 месяц Утро СПБ Подписка",
              "product_type": "morning"
            },
            {
              "product_id": "425320",
              "product_price": "2900",
              "product_name": "1 месяц СПБ Подписка",
              "product_type": "full"
            },
            {
              "product_id": "425476",
              "product_price": "3500",
              "product_name": "Мультикарта 1 месяц СПБ Подписка",
              "product_type": "mc_full"
            },
            {
              "product_id": "425194",
              "product_price": "1990",
              "product_name": "Первоначальный платеж",
              "product_type": "first_pay"
            }
          ]
        },
        {
          "id": 25,
          "name": "FH на Комендантском",
          "address": "Комендантский пр. д. 2, лит. А",
          "isPool": true,
          "category": "STD",
          "products": [
            {
              "product_id": "425419",
              "product_price": "1900",
              "product_name": "1 месяц Утро СПБ Подписка",
              "product_type": "morning"
            },
            {
              "product_id": "425423",
              "product_price": "2900",
              "product_name": "1 месяц СПБ Подписка",
              "product_type": "full"
            },
            {
              "product_id": "425448",
              "product_price": "3500",
              "product_name": "Мультикарта 1 месяц СПБ Подписка",
              "product_type": "mc_full"
            },
            {
              "product_id": "425242",
              "product_price": "1990",
              "product_name": "Первоначальный платеж",
              "product_type": "first_pay"
            }
          ]
        },
        {
          "id": 26,
          "name": "FH на Краснопутиловской",
          "address": "ул. Краснопутиловская, д 111, А",
          "isPool": true,
          "category": "STD",
          "products": [
            {
              "product_id": "425403",
              "product_price": "1900",
              "product_name": "1 месяц Утро СПБ Подписка",
              "product_type": "morning"
            },
            {
              "product_id": "425311",
              "product_price": "2900",
              "product_name": "1 месяц СПБ Подписка",
              "product_type": "full"
            },
            {
              "product_id": "425466",
              "product_price": "3500",
              "product_name": "Мультикарта 1 месяц СПБ Подписка",
              "product_type": "mc_full"
            },
            {
              "product_id": "425219",
              "product_price": "1990",
              "product_name": "Первоначальный платеж",
              "product_type": "first_pay"
            }
          ]
        },
        {
          "id": 27,
          "name": "FH на Культуры",
          "address": "пр. Культуры, д. 41, лит. А",
          "isPool": true,
          "category": "STD",
          "products": [
            {
              "product_id": "425418",
              "product_price": "1900",
              "product_name": "1 месяц Утро СПБ Подписка",
              "product_type": "morning"
            },
            {
              "product_id": "425422",
              "product_price": "2900",
              "product_name": "1 месяц СПБ Подписка",
              "product_type": "full"
            },
            {
              "product_id": "425420",
              "product_price": "3500",
              "product_name": "Мультикарта 1 месяц СПБ Подписка",
              "product_type": "mc_full"
            },
            {
              "product_id": "425236",
              "product_price": "1990",
              "product_name": "Первоначальный платеж",
              "product_type": "first_pay"
            }
          ]
        },
        {
          "id": 28,
          "name": "FH на Ладожской",
          "address": "пр. Карла Фаберже, д.8, лит. Е",
          "isPool": true,
          "category": "STD",
          "products": [
            {
              "product_id": "425334",
              "product_price": "1900",
              "product_name": "1 месяц Утро СПБ Подписка",
              "product_type": "morning"
            },
            {
              "product_id": "425292",
              "product_price": "2900",
              "product_name": "1 месяц СПБ Подписка",
              "product_type": "full"
            },
            {
              "product_id": "425450",
              "product_price": "3500",
              "product_name": "Мультикарта 1 месяц СПБ Подписка",
              "product_type": "mc_full"
            },
            {
              "product_id": "425239",
              "product_price": "1990",
              "product_name": "Первоначальный платеж",
              "product_type": "first_pay"
            }
          ]
        },
        {
          "id": 29,
          "name": "FH на Ленинском",
          "address": "Ленинский пр., д.160, лит. А",
          "isPool": true,
          "category": "STD",
          "products": [
            {
              "product_id": "425327",
              "product_price": "1900",
              "product_name": "1 месяц Утро СПБ Подписка",
              "product_type": "morning"
            },
            {
              "product_id": "425285",
              "product_price": "2900",
              "product_name": "1 месяц СПБ Подписка",
              "product_type": "full"
            },
            {
              "product_id": "425443",
              "product_price": "3500",
              "product_name": "Мультикарта 1 месяц СПБ Подписка",
              "product_type": "mc_full"
            },
            {
              "product_id": "425247",
              "product_price": "1990",
              "product_name": "Первоначальный платеж",
              "product_type": "first_pay"
            }
          ]
        },
        {
          "id": 30,
          "name": "FH на Маршака",
          "address": "пр.Маршака, д.10",
          "isPool": true,
          "category": "STD",
          "products": [
            {
              "product_id": "425410",
              "product_price": "1900",
              "product_name": "1 месяц Утро СПБ Подписка",
              "product_type": "morning"
            },
            {
              "product_id": "425318",
              "product_price": "2900",
              "product_name": "1 месяц СПБ Подписка",
              "product_type": "full"
            },
            {
              "product_id": "425474",
              "product_price": "3500",
              "product_name": "Мультикарта 1 месяц СПБ Подписка",
              "product_type": "mc_full"
            },
            {
              "product_id": "425196",
              "product_price": "1990",
              "product_name": "Первоначальный платеж",
              "product_type": "first_pay"
            }
          ]
        },
        {
          "id": 31,
          "name": "FH на Маршала Блюхера",
          "address": "пр. Маршала Блюхера, дом 9, корп. 3, лит. А",
          "isPool": true,
          "category": "STD",
          "products": [
            {
              "product_id": "425404",
              "product_price": "1900",
              "product_name": "1 месяц Утро СПБ Подписка",
              "product_type": "morning"
            },
            {
              "product_id": "425312",
              "product_price": "2900",
              "product_name": "1 месяц СПБ Подписка",
              "product_type": "full"
            },
            {
              "product_id": "425467",
              "product_price": "3500",
              "product_name": "Мультикарта 1 месяц СПБ Подписка",
              "product_type": "mc_full"
            },
            {
              "product_id": "425218",
              "product_price": "1990",
              "product_name": "Первоначальный платеж",
              "product_type": "first_pay"
            }
          ]
        },
        {
          "id": 32,
          "name": "FH на Маршала Говорова",
          "address": "ул. Маршала Говорова, д. 35, кор. 4",
          "isPool": true,
          "category": "STD",
          "products": [
            {
              "product_id": "425339",
              "product_price": "1900",
              "product_name": "1 месяц Утро СПБ Подписка",
              "product_type": "morning"
            },
            {
              "product_id": "425297",
              "product_price": "2900",
              "product_name": "1 месяц СПБ Подписка",
              "product_type": "full"
            },
            {
              "product_id": "425455",
              "product_price": "3500",
              "product_name": "Мультикарта 1 месяц СПБ Подписка",
              "product_type": "mc_full"
            },
            {
              "product_id": "425233",
              "product_price": "1990",
              "product_name": "Первоначальный платеж",
              "product_type": "first_pay"
            }
          ]
        },
        {
          "id": 33,
          "name": "FH на Мебельной",
          "address": "ул. Мебельная, д.1, корп. 2А",
          "isPool": true,
          "category": "STD",
          "products": [
            {
              "product_id": "425394",
              "product_price": "1900",
              "product_name": "1 месяц Утро СПБ Подписка",
              "product_type": "morning"
            },
            {
              "product_id": "425301",
              "product_price": "2900",
              "product_name": "1 месяц СПБ Подписка",
              "product_type": "full"
            },
            {
              "product_id": "425458",
              "product_price": "3500",
              "product_name": "Мультикарта 1 месяц СПБ Подписка",
              "product_type": "mc_full"
            },
            {
              "product_id": "425229",
              "product_price": "1990",
              "product_name": "Первоначальный платеж",
              "product_type": "first_pay"
            }
          ]
        },
        {
          "id": 34,
          "name": "FH на Наличной",
          "address": "Наличная улица, д.44 корп.1",
          "isPool": true,
          "category": "STD",
          "products": [
            {
              "product_id": "425406",
              "product_price": "1900",
              "product_name": "1 месяц Утро СПБ Подписка",
              "product_type": "morning"
            },
            {
              "product_id": "425314",
              "product_price": "2900",
              "product_name": "1 месяц СПБ Подписка",
              "product_type": "full"
            },
            {
              "product_id": "425469",
              "product_price": "3500",
              "product_name": "Мультикарта 1 месяц СПБ Подписка",
              "product_type": "mc_full"
            },
            {
              "product_id": "425215",
              "product_price": "1990",
              "product_name": "Первоначальный платеж",
              "product_type": "first_pay"
            }
          ]
        },
        {
          "id": 35,
          "name": "FH на Пискаревском",
          "address": "Пискаревский пр., д.25, лит. А",
          "isPool": true,
          "category": "STD",
          "products": [
            {
              "product_id": "425332",
              "product_price": "1900",
              "product_name": "1 месяц Утро СПБ Подписка",
              "product_type": "morning"
            },
            {
              "product_id": "425290",
              "product_price": "2900",
              "product_name": "1 месяц СПБ Подписка",
              "product_type": "full"
            },
            {
              "product_id": "425449",
              "product_price": "3500",
              "product_name": "Мультикарта 1 месяц СПБ Подписка",
              "product_type": "mc_full"
            },
            {
              "product_id": "425241",
              "product_price": "1990",
              "product_name": "Первоначальный платеж",
              "product_type": "first_pay"
            }
          ]
        },
        {
          "id": 36,
          "name": "FH на Пражской",
          "address": "ул. Пражская, д. 30, лит.А, корп. 2",
          "isPool": true,
          "category": "STD",
          "products": [
            {
              "product_id": "425336",
              "product_price": "1900",
              "product_name": "1 месяц Утро СПБ Подписка",
              "product_type": "morning"
            },
            {
              "product_id": "425294",
              "product_price": "2900",
              "product_name": "1 месяц СПБ Подписка",
              "product_type": "full"
            },
            {
              "product_id": "425451",
              "product_price": "3500",
              "product_name": "Мультикарта 1 месяц СПБ Подписка",
              "product_type": "mc_full"
            },
            {
              "product_id": "425237",
              "product_price": "1990",
              "product_name": "Первоначальный платеж",
              "product_type": "first_pay"
            }
          ]
        },
        {
          "id": 37,
          "name": "FH на Пулковском",
          "address": "Шереметьевская ул. 13 А",
          "isPool": true,
          "category": "STD",
          "products": [
            {
              "product_id": "425326",
              "product_price": "1900",
              "product_name": "1 месяц Утро СПБ Подписка",
              "product_type": "morning"
            },
            {
              "product_id": "425284",
              "product_price": "2900",
              "product_name": "1 месяц СПБ Подписка",
              "product_type": "full"
            },
            {
              "product_id": "425442",
              "product_price": "3500",
              "product_name": "Мультикарта 1 месяц СПБ Подписка",
              "product_type": "mc_full"
            },
            {
              "product_id": "425248",
              "product_price": "1990",
              "product_name": "Первоначальный платеж",
              "product_type": "first_pay"
            }
          ]
        },
        {
          "id": 38,
          "name": "FH на Савушкина",
          "address": "ул. Савушкина, д. 119., корп. 3",
          "isPool": true,
          "category": "STD",
          "products": [
            {
              "product_id": "425329",
              "product_price": "1900",
              "product_name": "1 месяц Утро СПБ Подписка",
              "product_type": "morning"
            },
            {
              "product_id": "425287",
              "product_price": "2900",
              "product_name": "1 месяц СПБ Подписка",
              "product_type": "full"
            },
            {
              "product_id": "425445",
              "product_price": "3500",
              "product_name": "Мультикарта 1 месяц СПБ Подписка",
              "product_type": "mc_full"
            },
            {
              "product_id": "425245",
              "product_price": "1990",
              "product_name": "Первоначальный платеж",
              "product_type": "first_pay"
            }
          ]
        },
        {
          "id": 39,
          "name": "FH на Северном",
          "address": "Северный пр. д. 40 литер А",
          "isPool": true,
          "category": "STD",
          "products": [
            {
              "product_id": "425402",
              "product_price": "1900",
              "product_name": "1 месяц Утро СПБ Подписка",
              "product_type": "morning"
            },
            {
              "product_id": "425310",
              "product_price": "2900",
              "product_name": "1 месяц СПБ Подписка",
              "product_type": "full"
            },
            {
              "product_id": "425465",
              "product_price": "3500",
              "product_name": "Мультикарта 1 месяц СПБ Подписка",
              "product_type": "mc_full"
            },
            {
              "product_id": "425220",
              "product_price": "1990",
              "product_name": "Первоначальный платеж",
              "product_type": "first_pay"
            }
          ]
        },
        {
          "id": 40,
          "name": "FH на Стачек",
          "address": "пр. Стачек д.47 лит Ж",
          "isPool": true,
          "category": "STD",
          "products": [
            {
              "product_id": "425397",
              "product_price": "1900",
              "product_name": "1 месяц Утро СПБ Подписка",
              "product_type": "morning"
            },
            {
              "product_id": "425305",
              "product_price": "2900",
              "product_name": "1 месяц СПБ Подписка",
              "product_type": "full"
            },
            {
              "product_id": "425461",
              "product_price": "3500",
              "product_name": "Мультикарта 1 месяц СПБ Подписка",
              "product_type": "mc_full"
            },
            {
              "product_id": "425225",
              "product_price": "1990",
              "product_name": "Первоначальный платеж",
              "product_type": "first_pay"
            }
          ]
        },
        {
          "id": 41,
          "name": "FH на Таллинском",
          "address": "Таллинское шоссе, 40/а",
          "isPool": true,
          "category": "STD",
          "products": [
            {
              "product_id": "425396",
              "product_price": "1900",
              "product_name": "1 месяц Утро СПБ Подписка",
              "product_type": "morning"
            },
            {
              "product_id": "425304",
              "product_price": "2900",
              "product_name": "1 месяц СПБ Подписка",
              "product_type": "full"
            },
            {
              "product_id": "425359",
              "product_price": "3500",
              "product_name": "Мультикарта 1 месяц СПБ Подписка",
              "product_type": "mc_full"
            },
            {
              "product_id": "425226",
              "product_price": "1990",
              "product_name": "Первоначальный платеж",
              "product_type": "first_pay"
            }
          ]
        },
        {
          "id": 42,
          "name": "FH на Фучика",
          "address": "Фучика д2, лит. А",
          "isPool": true,
          "category": "STD",
          "products": [
            {
              "product_id": "425395",
              "product_price": "1900",
              "product_name": "1 месяц Утро СПБ Подписка",
              "product_type": "morning"
            },
            {
              "product_id": "425303",
              "product_price": "2900",
              "product_name": "1 месяц СПБ Подписка",
              "product_type": "full"
            },
            {
              "product_id": "425460",
              "product_price": "3500",
              "product_name": "Мультикарта 1 месяц СПБ Подписка",
              "product_type": "mc_full"
            },
            {
              "product_id": "425227",
              "product_price": "1990",
              "product_name": "Первоначальный платеж",
              "product_type": "first_pay"
            }
          ]
        },
        {
          "id": 43,
          "name": "FH на Хасанской",
          "address": "ул. Хасанская, 10",
          "isPool": true,
          "category": "STD",
          "products": [
            {
              "product_id": "425407",
              "product_price": "1900",
              "product_name": "1 месяц Утро СПБ Подписка",
              "product_type": "morning"
            },
            {
              "product_id": "425315",
              "product_price": "2900",
              "product_name": "1 месяц СПБ Подписка",
              "product_type": "full"
            },
            {
              "product_id": "425370",
              "product_price": "3500",
              "product_name": "Мультикарта 1 месяц СПБ Подписка",
              "product_type": "mc_full"
            },
            {
              "product_id": "425214",
              "product_price": "1990",
              "product_name": "Первоначальный платеж",
              "product_type": "first_pay"
            }
          ]
        },
        {
          "id": 44,
          "name": "FH на Чкаловской",
          "address": "ул. Большая Разночинная, д. 25 А",
          "isPool": true,
          "category": "STD",
          "products": [
            {
              "product_id": "425325",
              "product_price": "1900",
              "product_name": "1 месяц Утро СПБ Подписка",
              "product_type": "morning"
            },
            {
              "product_id": "425283",
              "product_price": "2900",
              "product_name": "1 месяц СПБ Подписка",
              "product_type": "full"
            },
            {
              "product_id": "425441",
              "product_price": "3500",
              "product_name": "Мультикарта 1 месяц СПБ Подписка",
              "product_type": "mc_full"
            },
            {
              "product_id": "425249",
              "product_price": "1990",
              "product_name": "Первоначальный платеж",
              "product_type": "first_pay"
            }
          ]
        },
        {
          "id": 45,
          "name": "FH на Шаврова",
          "address": "ул.Шаврова, 26",
          "isPool": true,
          "category": "STD",
          "products": [
            {
              "product_id": "425408",
              "product_price": "1900",
              "product_name": "1 месяц Утро СПБ Подписка",
              "product_type": "morning"
            },
            {
              "product_id": "425316",
              "product_price": "2900",
              "product_name": "1 месяц СПБ Подписка",
              "product_type": "full"
            },
            {
              "product_id": "425472",
              "product_price": "3500",
              "product_name": "Мультикарта 1 месяц СПБ Подписка",
              "product_type": "mc_full"
            },
            {
              "product_id": "425198",
              "product_price": "1990",
              "product_name": "Первоначальный платеж",
              "product_type": "first_pay"
            }
          ]
        },
        {
          "id": 46,
          "name": "FH на Политехнической",
          "address": "ул. Политехническая д. 6",
          "isPool": true,
          "category": "STD",
          "products": [
            {
              "product_id": "425415",
              "product_price": "1900",
              "product_name": "1 месяц Утро СПБ Подписка",
              "product_type": "morning"
            },
            {
              "product_id": "425324",
              "product_price": "2900",
              "product_name": "1 месяц СПБ Подписка",
              "product_type": "full"
            },
            {
              "product_id": "425378",
              "product_price": "3500",
              "product_name": "Мультикарта 1 месяц СПБ Подписка",
              "product_type": "mc_full"
            },
            {
              "product_id": "425186",
              "product_price": "1990",
              "product_name": "Первоначальный платеж",
              "product_type": "first_pay"
            }
          ]
        },
        {
          "id": 47,
          "name": "FH на Крестовском",
          "address": "пр. Крестовский, д. 24 Б",
          "isPool": true,
          "category": "STD",
          "products": [
            {
              "product_id": "425438",
              "product_price": "1900",
              "product_name": "1 месяц Утро СПБ Подписка",
              "product_type": "morning"
            },
            {
              "product_id": "425430",
              "product_price": "2900",
              "product_name": "1 месяц СПБ Подписка",
              "product_type": "full"
            },
            {
              "product_id": "425452",
              "product_price": "3500",
              "product_name": "Мультикарта 1 месяц СПБ Подписка",
              "product_type": "mc_full"
            },
            {
              "product_id": "425426",
              "product_price": "1990",
              "product_name": "Первоначальный платеж",
              "product_type": "first_pay"
            }
          ]
        }
      ]
    }
  ]
}
